django_better_auth_oidc/__init__.py
django_better_auth_oidc/auth.py
django_better_auth_oidc/urls.py
django_better_auth_oidc/views.py
django_better_auth_oidc-0.2.0.dist-info/LICENSE
django_better_auth_oidc-0.2.0.dist-info/LICENSE.upstream
django_better_auth_oidc-0.2.0.dist-info/LICENSE.upstream.bsd
django_better_auth_oidc-0.2.0.dist-info/METADATA
django_better_auth_oidc-0.2.0.dist-info/WHEEL
django_better_auth_oidc-0.2.0.dist-info/top_level.txt
django_better_auth_oidc-0.2.0.dist-info/zip-safe
django_better_auth_oidc-0.2.0.dist-info/RECORD
