Metadata-Version: 2.1
Name: django-better-auth-oidc
Version: 0.2.0
Summary: Better OpenID Connect authentication support for Django
Home-page: https://github.com/jouleworks/django-better-auth-oidc
Author: Jouleworks Development Contributors
Author-email: hello@jouleworksdev.com
License: MIT
Keywords: django auth oauth openid oidc social ldap
Classifier: Development Status :: 5 - Production/Stable
Classifier: Framework :: Django
Classifier: Framework :: Django :: 4.0
Classifier: Framework :: Django :: 4.1
Classifier: Framework :: Django :: 4.2
Classifier: Intended Audience :: System Administrators
Classifier: License :: OSI Approved :: MIT License
Classifier: License :: OSI Approved :: BSD License
Classifier: Programming Language :: Python
Classifier: Programming Language :: Python :: 3
Classifier: Programming Language :: Python :: 3 :: Only
Classifier: Programming Language :: Python :: 3.5
Classifier: Programming Language :: Python :: 3.6
Classifier: Programming Language :: Python :: 3.7
Classifier: Programming Language :: Python :: 3.8
Classifier: Programming Language :: Python :: 3.9
Classifier: Programming Language :: Python :: 3.10
Classifier: Programming Language :: Python :: 3.11
Classifier: Topic :: System :: Systems Administration :: Authentication/Directory
License-File: LICENSE
License-File: LICENSE.upstream
License-File: LICENSE.upstream.bsd
Requires-Dist: django >=4.0.0
Requires-Dist: openid-connect
